Metadata-Version: 2.1
Name: amet
Version: 0.4
Summary: A library to read complex configuration from environment variables.
Home-page: https://github.com/maurodec/amet
Author: Mauro de Carvalho
Author-email: mauro.dec@gmail.com
License: UNKNOWN
Download-URL: https://github.com/maurodec/amet/archive/0.4.tar.gz
Project-URL: Source, https://github.com/maurodec/amet
Project-URL: Bug Reports, https://github.com/maurodec/amet/issues
Keywords: confiuration configuration-management environment environment-variables heroku
Platform: UNKNOWN
Classifier: Development Status :: 5 - Production/Stable
Classifier: License :: OSI Approved :: MIT License
Classifier: Intended Audience :: Developers
Classifier: Intended Audience :: System Administrators
Classifier: Programming Language :: Python :: 2
Classifier: Programming Language :: Python :: 3
Classifier: Operating System :: POSIX :: BSD
Classifier: Operating System :: POSIX :: Linux
Classifier: Operating System :: Microsoft :: Windows
Classifier: Topic :: System :: Software Distribution
Classifier: Topic :: System :: Systems Administration
